nummpi/__init__.py
nummpi/brand.py
nummpi/competitor.py
nummpi/content.py
nummpi/eda.py
nummpi/engagement.py
nummpi/hashtag.py
nummpi/location.py
nummpi/network.py
nummpi/preprocessing.py
nummpi/sentiment.py
nummpi/trend.py
nummpi-2.2.1.dist-info/LICENSE
nummpi-2.2.1.dist-info/METADATA
nummpi-2.2.1.dist-info/WHEEL
nummpi-2.2.1.dist-info/top_level.txt
nummpi-2.2.1.dist-info/RECORD
